pyIndicatorAPI/__init__.py
pyIndicatorAPI/indicators.py
pyIndicatorAPI/handlers/__init__.py
pyIndicatorAPI/handlers/inderrhandler.py
pyIndicatorAPI/tests/__init__.py
pyIndicatorAPI/tests/indicator_tests.py
pyIndicatorAPI-0.0.3.dist-info/METADATA
pyIndicatorAPI-0.0.3.dist-info/WHEEL
pyIndicatorAPI-0.0.3.dist-info/top_level.txt
pyIndicatorAPI-0.0.3.dist-info/RECORD
